telepager/__init__.py
telepager/_compat.py
telepager/design.py
telepager/flag.py
telepager/i18n.py
telepager/manager.py
telepager/paginator.py
telepager/structs.py
telepager-0.1.0.dist-info/LICENSE
telepager-0.1.0.dist-info/METADATA
telepager-0.1.0.dist-info/WHEEL
telepager-0.1.0.dist-info/RECORD
