Metadata-Version: 2.1
Name: telepager
Version: 0.1.0
Summary: A fancy paginator for your Telegram bots
License: MIT
Author: prostomarkeloff
Requires-Python: >=3.12,<4.0
Classifier: License :: OSI Approved :: MIT License
Classifier: Programming Language :: Python :: 3
Classifier: Programming Language :: Python :: 3.12
